Juicy/__init__.py
Juicy/client.py
Juicy/command_pb2.py
Juicy/command_pb2_grpc.py
Juicy-0.0.2.dist-info/DESCRIPTION.rst
Juicy-0.0.2.dist-info/METADATA
Juicy-0.0.2.dist-info/RECORD
Juicy-0.0.2.dist-info/WHEEL
Juicy-0.0.2.dist-info/metadata.json
Juicy-0.0.2.dist-info/top_level.txt
