Metadata-Version: 2.0
Name: Juicy
Version: 0.0.2
Summary: Juicy database python client
Home-page: https://github.com/salamer/Juicy/python
Author: aljun
Author-email: salamer_gaga@163.com
License: Apache
Download-URL: https://github.com/salamer/Juicy/python
Keywords: database,client,distributed-system
Platform: UNKNOWN
Classifier: Development Status :: 3 - Alpha
Classifier: License :: OSI Approved :: Apache Software License
Classifier: Environment :: Web Environment
Classifier: Programming Language :: Python :: 2.7
Classifier: Topic :: Internet :: WWW/HTTP
Classifier: Topic :: Software Development :: Libraries :: Python Modules
Requires-Dist: grpcio
